nbases/__init__.py
nbases/errors.py
nbases/nbase.py
nbases-1.0.0.dist-info/LICENSE
nbases-1.0.0.dist-info/METADATA
nbases-1.0.0.dist-info/WHEEL
nbases-1.0.0.dist-info/top_level.txt
nbases-1.0.0.dist-info/RECORD
